getzeit/__init__.py
getzeit/__main__.py
getzeit-0.3.1.dist-info/COPYING
getzeit-0.3.1.dist-info/METADATA
getzeit-0.3.1.dist-info/WHEEL
getzeit-0.3.1.dist-info/entry_points.txt
getzeit-0.3.1.dist-info/top_level.txt
getzeit-0.3.1.dist-info/RECORD
