Metadata-Version: 2.1
Name: getzeit
Version: 0.3.1
Summary: Download DIE ZEIT newspaper in various formats
Author-email: mahlzahn <mahlzahn@posteo.de>
License: GNU General Public License v3 or later (GPLv3+)
Project-URL: Source, https://codeberg.org/mahlzahn/getzeit
Project-URL: Issues, https://codeberg.org/mahlzahn/getzeit/issues
Classifier: Development Status :: 4 - Beta
Classifier: Environment :: Console
Classifier: Topic :: Utilities
Classifier: Operating System :: POSIX :: Linux
Classifier: Programming Language :: Python :: 3
Classifier: License :: OSI Approved :: GNU General Public License v3 or later (GPLv3+)
Requires-Python: >=3.8
License-File: COPYING
Requires-Dist: browser_cookie3>=0.20.1
Requires-Dist: requests
Provides-Extra: argcomplete
Requires-Dist: argcomplete; extra == "argcomplete"
Provides-Extra: full
Requires-Dist: argcomplete; extra == "full"
